pysimpleapp/__init__.py
pysimpleapp/message.py
pysimpleapp/threads/__init__.py
pysimpleapp/threads/examples.py
pysimpleapp/threads/simple_threads.py
tests/__init__.py
tests/test_pysimpleapp.py
pysimpleapp-0.1.3.dist-info/AUTHORS.rst
pysimpleapp-0.1.3.dist-info/METADATA
pysimpleapp-0.1.3.dist-info/WHEEL
pysimpleapp-0.1.3.dist-info/top_level.txt
pysimpleapp-0.1.3.dist-info/RECORD
