Metadata-Version: 2.1
Name: pysimpleapp
Version: 0.1.3
Summary: Simple framework for applications in python
Home-page: https://github.com/MagpieEmbedded/pysimpleapp
Author: Tim Guite
Author-email: magpieembedded@gmail.com
License: MIT license
Keywords: pysimpleapp
Platform: UNKNOWN
Classifier: Development Status :: 2 - Pre-Alpha
Classifier: Intended Audience :: Developers
Classifier: License :: OSI Approved :: MIT License
Classifier: Natural Language :: English
Classifier: Programming Language :: Python :: 3.6
Classifier: Programming Language :: Python :: 3.7
